cat_merge/__init__.py
cat_merge/cli.py
cat_merge/duckdb_merge.py
cat_merge/duckdb_qc.py
cat_merge/duckdb_utils.py
cat_merge/file_utils.py
cat_merge/mapping_utils.py
cat_merge/merge.py
cat_merge/merge_utils.py
cat_merge/model/__init__.py
cat_merge/model/merged_kg.py
cat_merge/qc.py
cat_merge/qc_diff_utils.py
cat_merge/qc_stats.py
cat_merge/qc_utils.py
cat_merge/schema_utils.py
cat_merge-1.0.2.dist-info/METADATA
cat_merge-1.0.2.dist-info/WHEEL
cat_merge-1.0.2.dist-info/entry_points.txt
cat_merge-1.0.2.dist-info/RECORD
