Metadata-Version: 2.3
Name: cat-merge
Version: 1.0.2
Summary: 
Author: Monarch Initiative
Author-email: info@monarchinitiative.org
Requires-Python: >=3.10,<4.0
Classifier: Programming Language :: Python :: 3
Classifier: Programming Language :: Python :: 3.10
Classifier: Programming Language :: Python :: 3.11
Classifier: Programming Language :: Python :: 3.12
Classifier: Programming Language :: Python :: 3.13
Requires-Dist: click (>=8,<9)
Requires-Dist: duckdb (>=1.0.0,<2.0.0)
Requires-Dist: linkml-runtime (>=1.7.0,<2.0.0)
Requires-Dist: mkdocs (>=1.3.0,<2.0.0)
Requires-Dist: pandas (>=2.0.0,<3.0.0)
Requires-Dist: pyyaml (>=6.0,<7.0)
Requires-Dist: scipy (>=1.9,<2.0.0)
